{
  "model_path": "/cyq/hase/model_zoo/models/resnet18_bs16_224x224.onnx",
  "record_json": "/cyq/hase/ort_analysis/ort_kernel_record/resnet18.json",
  "kernel_onnx_dir": "/cyq/hase/kernel_model/kernel_onnx",
  "warmup": 0,
  "loops": 1,
  "total_latency_ms": 1031.956508755684,
  "kernels": [
    {
      "index": 1,
      "node_name": "/conv1/Conv",
      "kernel_type": "Conv_Relu",
      "kernel_id": "Conv_Relu_bs16_3c224x224_k7x7",
      "kernel_onnx": "/cyq/hase/kernel_model/kernel_onnx/Conv_Relu_bs16_3c224x224_k7x7.onnx",
      "input_shape": "16x3x224x224",
      "latency_ms": 103.1577568501234
    },
    {
      "index": 2,
      "node_name": "/maxpool/MaxPool",
      "kernel_type": "MaxPool",
      "kernel_id": "MaxPool_bs16_64c112x112_k3x3",
      "kernel_onnx": "/cyq/hase/kernel_model/kernel_onnx/MaxPool_bs16_64c112x112_k3x3.onnx",
      "input_shape": "16x64x112x112",
      "latency_ms": 177.8971329331398
    },
    {
      "index": 3,
      "node_name": "/layer1/layer1.0/conv1/Conv",
      "kernel_type": "Conv_Relu",
      "kernel_id": "Conv_Relu_bs16_64c56x56_k3x3",
      "kernel_onnx": "/cyq/hase/kernel_model/kernel_onnx/Conv_Relu_bs16_64c56x56_k3x3.onnx",
      "input_shape": "16x64x56x56",
      "latency_ms": 16.44160784780979
    },
    {
      "index": 4,
      "node_name": "/layer1/layer1.0/conv2/Conv",
      "kernel_type": "Conv_Add_Relu",
      "kernel_id": "Conv_Add_Relu_bs16_64c56x56_k3x3",
      "kernel_onnx": "/cyq/hase/kernel_model/kernel_onnx/Conv_Add_Relu_bs16_64c56x56_k3x3.onnx",
      "input_shape": "16x64x56x56",
      "latency_ms": 20.413996651768684
    },
    {
      "index": 5,
      "node_name": "/layer1/layer1.1/conv1/Conv",
      "kernel_type": "Conv_Relu",
      "kernel_id": "Conv_Relu_bs16_64c56x56_k3x3",
      "kernel_onnx": "/cyq/hase/kernel_model/kernel_onnx/Conv_Relu_bs16_64c56x56_k3x3.onnx",
      "input_shape": "16x64x56x56",
      "latency_ms": 17.253464087843895
    },
    {
      "index": 6,
      "node_name": "/layer1/layer1.1/conv2/Conv",
      "kernel_type": "Conv_Add_Relu",
      "kernel_id": "Conv_Add_Relu_bs16_64c56x56_k3x3",
      "kernel_onnx": "/cyq/hase/kernel_model/kernel_onnx/Conv_Add_Relu_bs16_64c56x56_k3x3.onnx",
      "input_shape": "16x64x56x56",
      "latency_ms": 191.94711185991764
    },
    {
      "index": 7,
      "node_name": "/layer2/layer2.0/conv1/Conv",
      "kernel_type": "Conv_Relu",
      "kernel_id": "Conv_Relu_bs16_64c56x56_k3x3",
      "kernel_onnx": "/cyq/hase/kernel_model/kernel_onnx/Conv_Relu_bs16_64c56x56_k3x3.onnx",
      "input_shape": "16x64x56x56",
      "latency_ms": 17.568988725543022
    },
    {
      "index": 8,
      "node_name": "/layer2/layer2.0/conv2/Conv",
      "kernel_type": "Conv",
      "kernel_id": "Conv_bs16_128c28x28_k3x3",
      "kernel_onnx": "/cyq/hase/kernel_model/kernel_onnx/Conv_bs16_128c28x28_k3x3.onnx",
      "input_shape": "16x128x28x28",
      "latency_ms": 9.586293250322342
    },
    {
      "index": 9,
      "node_name": "/layer2/layer2.0/downsample/downsample.0/Conv",
      "kernel_type": "Conv_Add_Relu",
      "kernel_id": "Conv_Add_Relu_bs16_64c56x56_k1x1",
      "kernel_onnx": "/cyq/hase/kernel_model/kernel_onnx/Conv_Add_Relu_bs16_64c56x56_k1x1.onnx",
      "input_shape": "16x64x56x56",
      "latency_ms": 7.05217570066452
    },
    {
      "index": 10,
      "node_name": "/layer2/layer2.1/conv1/Conv",
      "kernel_type": "Conv_Relu",
      "kernel_id": "Conv_Relu_bs16_128c28x28_k3x3",
      "kernel_onnx": "/cyq/hase/kernel_model/kernel_onnx/Conv_Relu_bs16_128c28x28_k3x3.onnx",
      "input_shape": "16x128x28x28",
      "latency_ms": 10.455278679728508
    },
    {
      "index": 11,
      "node_name": "/layer2/layer2.1/conv2/Conv",
      "kernel_type": "Conv_Add_Relu",
      "kernel_id": "Conv_Add_Relu_bs16_128c28x28_k3x3",
      "kernel_onnx": "/cyq/hase/kernel_model/kernel_onnx/Conv_Add_Relu_bs16_128c28x28_k3x3.onnx",
      "input_shape": "16x128x28x28",
      "latency_ms": 9.996084496378899
    },
    {
      "index": 12,
      "node_name": "/layer3/layer3.0/conv1/Conv",
      "kernel_type": "Conv_Relu",
      "kernel_id": "Conv_Relu_bs16_128c28x28_k3x3",
      "kernel_onnx": "/cyq/hase/kernel_model/kernel_onnx/Conv_Relu_bs16_128c28x28_k3x3.onnx",
      "input_shape": "16x128x28x28",
      "latency_ms": 178.56819555163383
    },
    {
      "index": 13,
      "node_name": "/layer3/layer3.0/conv2/Conv",
      "kernel_type": "Conv",
      "kernel_id": "Conv_bs16_256c14x14_k3x3",
      "kernel_onnx": "/cyq/hase/kernel_model/kernel_onnx/Conv_bs16_256c14x14_k3x3.onnx",
      "input_shape": "16x256x14x14",
      "latency_ms": 11.131664738059044
    },
    {
      "index": 14,
      "node_name": "/layer3/layer3.0/downsample/downsample.0/Conv",
      "kernel_type": "Conv_Add_Relu",
      "kernel_id": "Conv_Add_Relu_bs16_128c28x28_k1x1",
      "kernel_onnx": "/cyq/hase/kernel_model/kernel_onnx/Conv_Add_Relu_bs16_128c28x28_k1x1.onnx",
      "input_shape": "16x128x28x28",
      "latency_ms": 5.569513887166977
    },
    {
      "index": 15,
      "node_name": "/layer3/layer3.1/conv1/Conv",
      "kernel_type": "Conv_Relu",
      "kernel_id": "Conv_Relu_bs16_256c14x14_k3x3",
      "kernel_onnx": "/cyq/hase/kernel_model/kernel_onnx/Conv_Relu_bs16_256c14x14_k3x3.onnx",
      "input_shape": "16x256x14x14",
      "latency_ms": 10.923855006694794
    },
    {
      "index": 16,
      "node_name": "/layer3/layer3.1/conv2/Conv",
      "kernel_type": "Conv_Add_Relu",
      "kernel_id": "Conv_Add_Relu_bs16_256c14x14_k3x3",
      "kernel_onnx": "/cyq/hase/kernel_model/kernel_onnx/Conv_Add_Relu_bs16_256c14x14_k3x3.onnx",
      "input_shape": "16x256x14x14",
      "latency_ms": 12.340513989329338
    },
    {
      "index": 17,
      "node_name": "/layer4/layer4.0/conv1/Conv",
      "kernel_type": "Conv_Relu",
      "kernel_id": "Conv_Relu_bs16_256c14x14_k3x3",
      "kernel_onnx": "/cyq/hase/kernel_model/kernel_onnx/Conv_Relu_bs16_256c14x14_k3x3.onnx",
      "input_shape": "16x256x14x14",
      "latency_ms": 10.563863441348076
    },
    {
      "index": 18,
      "node_name": "/layer4/layer4.0/conv2/Conv",
      "kernel_type": "Conv",
      "kernel_id": "Conv_bs16_512c7x7_k3x3",
      "kernel_onnx": "/cyq/hase/kernel_model/kernel_onnx/Conv_bs16_512c7x7_k3x3.onnx",
      "input_shape": "16x512x7x7",
      "latency_ms": 15.623446553945541
    },
    {
      "index": 19,
      "node_name": "/layer4/layer4.0/downsample/downsample.0/Conv",
      "kernel_type": "Conv_Add_Relu",
      "kernel_id": "Conv_Add_Relu_bs16_256c14x14_k1x1",
      "kernel_onnx": "/cyq/hase/kernel_model/kernel_onnx/Conv_Add_Relu_bs16_256c14x14_k1x1.onnx",
      "input_shape": "16x256x14x14",
      "latency_ms": 5.077037960290909
    },
    {
      "index": 20,
      "node_name": "/layer4/layer4.1/conv1/Conv",
      "kernel_type": "Conv_Relu",
      "kernel_id": "Conv_Relu_bs16_512c7x7_k3x3",
      "kernel_onnx": "/cyq/hase/kernel_model/kernel_onnx/Conv_Relu_bs16_512c7x7_k3x3.onnx",
      "input_shape": "16x512x7x7",
      "latency_ms": 15.353413298726082
    },
    {
      "index": 21,
      "node_name": "/layer4/layer4.1/conv2/Conv",
      "kernel_type": "Conv_Add_Relu",
      "kernel_id": "Conv_Add_Relu_bs16_512c7x7_k3x3",
      "kernel_onnx": "/cyq/hase/kernel_model/kernel_onnx/Conv_Add_Relu_bs16_512c7x7_k3x3.onnx",
      "input_shape": "16x512x7x7",
      "latency_ms": 17.892539501190186
    },
    {
      "index": 22,
      "node_name": "/avgpool/GlobalAveragePool",
      "kernel_type": "GlobalAveragePool",
      "kernel_id": "GlobalAveragePool_bs16_512c7x7",
      "kernel_onnx": "/cyq/hase/kernel_model/kernel_onnx/GlobalAveragePool_bs16_512c7x7.onnx",
      "input_shape": "16x512x7x7",
      "latency_ms": 164.1507875174284
    },
    {
      "index": 23,
      "node_name": "/Flatten",
      "kernel_type": "Flatten",
      "kernel_id": "Flatten_bs16_512c1x1",
      "kernel_onnx": "/cyq/hase/kernel_model/kernel_onnx/Flatten_bs16_512c1x1.onnx",
      "input_shape": "16x512x1x1",
      "latency_ms": 0.6720628589391708
    },
    {
      "index": 24,
      "node_name": "/fc/Gemm",
      "kernel_type": "Gemm",
      "kernel_id": "Gemm_bs16_512",
      "kernel_onnx": "/cyq/hase/kernel_model/kernel_onnx/Gemm_bs16_512.onnx",
      "input_shape": "16x512",
      "latency_ms": 2.31972336769104
    }
  ]
}